setup.py
jingo_markdown/__init__.py
jingo_markdown/extensions.py
jingo_markdown/helpers.py
jingo_markdown.egg-info/PKG-INFO
jingo_markdown.egg-info/SOURCES.txt
jingo_markdown.egg-info/dependency_links.txt
jingo_markdown.egg-info/not-zip-safe
jingo_markdown.egg-info/requires.txt
jingo_markdown.egg-info/top_level.txt