Metadata-Version: 1.1
Name: jingo-markdown
Version: 1.3
Summary: Jingo (Jinja2) extension and filter for parse markdown text markup.
Home-page: https://github.com/mayapurmedia/jingo-markdown
Author: Prahlad Nrsimha Das - Petr Vacha
Author-email: pnd@mayapurmedia.com
License: UNKNOWN
Platform: UNKNOWN
Classifier: Environment :: Web Environment
Classifier: Intended Audience :: Developers
Classifier: Operating System :: OS Independent
Classifier: Programming Language :: Python
Classifier: Framework :: Django
Classifier: License :: OSI Approved :: MIT License
Classifier: Topic :: Software Development :: Code Generators
Classifier: Topic :: Text Processing :: Markup
